upmcli/__init__.py
upmcli/cli.py
upmcli-0.0.1.dist-info/DESCRIPTION.rst
upmcli-0.0.1.dist-info/LICENSE.txt
upmcli-0.0.1.dist-info/METADATA
upmcli-0.0.1.dist-info/RECORD
upmcli-0.0.1.dist-info/WHEEL
upmcli-0.0.1.dist-info/entry_points.txt
upmcli-0.0.1.dist-info/metadata.json
upmcli-0.0.1.dist-info/top_level.txt
